seselab/__init__.py
seselab/__main__.py
seselab/bench.py
seselab/bignum.asm
seselab/compiler.py
seselab/cpu.py
seselab/exn.py
seselab/memory.py
seselab/probe.py
seselab-0.1.dist-info/METADATA
seselab-0.1.dist-info/WHEEL
seselab-0.1.dist-info/entry_points.txt
seselab-0.1.dist-info/top_level.txt
seselab-0.1.dist-info/RECORD
