Metadata-Version: 2.1
Name: seselab
Version: 0.1
Summary: SeseLab: a software platform for teaching physical attacks
Home-page: https://pablo.rauzy.name/software.html#seselab
Author: Pablo Rauzy
Author-email: pr_NOSPAM@up8.edu
License: GNU AGPL v3+
Platform: UNKNOWN
